rplayground_mcp/__init__.py
rplayground_mcp/cli_basic.py
rplayground_mcp/configuration.py
rplayground_mcp/mcp_cli.py
rplayground_mcp/prompts.py
rplayground_mcp/session_manager.py
rplayground_mcp/session_manager_interface.py
rplayground_mcp/utils.py
rplayground_mcp-0.1.2.dist-info/METADATA
rplayground_mcp-0.1.2.dist-info/WHEEL
rplayground_mcp-0.1.2.dist-info/entry_points.txt
rplayground_mcp-0.1.2.dist-info/top_level.txt
rplayground_mcp-0.1.2.dist-info/RECORD
